nem_stats.cpython-312-aarch64-linux-gnu.so
ppanggolin/__init__.py
ppanggolin/edge.py
ppanggolin/geneFamily.py
ppanggolin/genetic_codes.py
ppanggolin/genome.py
ppanggolin/main.py
ppanggolin/metadata.py
ppanggolin/pangenome.py
ppanggolin/region.py
ppanggolin/utils.py
ppanggolin/RGP/__init__.py
ppanggolin/RGP/genomicIsland.py
ppanggolin/RGP/rgp_cluster.py
ppanggolin/RGP/spot.py
ppanggolin/align/__init__.py
ppanggolin/align/alignOnPang.py
ppanggolin/annotate/__init__.py
ppanggolin/annotate/annotate.py
ppanggolin/annotate/synta.py
ppanggolin/annotate/rRNA_DB/RF00001.cm
ppanggolin/annotate/rRNA_DB/RF00177.cm
ppanggolin/annotate/rRNA_DB/RF01959.cm
ppanggolin/annotate/rRNA_DB/RF02540.cm
ppanggolin/annotate/rRNA_DB/RF02541.cm
ppanggolin/annotate/rRNA_DB/rRNA_arch.cm
ppanggolin/annotate/rRNA_DB/rRNA_arch.cm.i1f
ppanggolin/annotate/rRNA_DB/rRNA_arch.cm.i1i
ppanggolin/annotate/rRNA_DB/rRNA_arch.cm.i1m
ppanggolin/annotate/rRNA_DB/rRNA_arch.cm.i1p
ppanggolin/annotate/rRNA_DB/rRNA_bact.cm
ppanggolin/annotate/rRNA_DB/rRNA_bact.cm.i1f
ppanggolin/annotate/rRNA_DB/rRNA_bact.cm.i1i
ppanggolin/annotate/rRNA_DB/rRNA_bact.cm.i1m
ppanggolin/annotate/rRNA_DB/rRNA_bact.cm.i1p
ppanggolin/cluster/__init__.py
ppanggolin/cluster/cluster.py
ppanggolin/context/__init__.py
ppanggolin/context/searchGeneContext.py
ppanggolin/figures/__init__.py
ppanggolin/figures/draw_spot.py
ppanggolin/figures/drawing.py
ppanggolin/figures/tile_plot.py
ppanggolin/figures/ucurve.py
ppanggolin/formats/__init__.py
ppanggolin/formats/readBinaries.py
ppanggolin/formats/writeAnnotations.py
ppanggolin/formats/writeBinaries.py
ppanggolin/formats/writeFlatGenomes.py
ppanggolin/formats/writeFlatMetadata.py
ppanggolin/formats/writeFlatPangenome.py
ppanggolin/formats/writeMSA.py
ppanggolin/formats/writeMetadata.py
ppanggolin/formats/writeSequences.py
ppanggolin/formats/write_proksee.py
ppanggolin/graph/__init__.py
ppanggolin/graph/makeGraph.py
ppanggolin-2.2.5.dist-info/METADATA
ppanggolin-2.2.5.dist-info/WHEEL
ppanggolin-2.2.5.dist-info/entry_points.txt
ppanggolin-2.2.5.dist-info/top_level.txt
ppanggolin-2.2.5.dist-info/RECORD
ppanggolin-2.2.5.dist-info/licenses/LICENSE.txt
