Metadata-Version: 2.4
Name: PPanGGOLiN
Version: 2.2.5
Summary: Pangenome analysis suite
Author: Guillaume Gautreau, Adelme Bazin, Jérôme Arnoux, Jean Mainguy
Maintainer: Guillaume Gautreau, Adelme Bazin, Jérôme Arnoux, Jean Mainguy
License: 
Project-URL: Homepage, https://labgem.genoscope.cns.fr/2023/04/27/ppanggolin/
Project-URL: Repository, https://github.com/labgem/PPanGGOLiN/
Project-URL: Documentation, https://ppanggolin.readthedocs.io
Keywords: Pangenomics,Comparative genomics,Bioinformatics,Prokaryote
Classifier: Development Status :: 5 - Production/Stable
Classifier: Environment :: Console
Classifier: Intended Audience :: Science/Research
Classifier: License :: OSI Approved :: CEA CNRS Inria Logiciel Libre License, version 2.1 (CeCILL-2.1)
Classifier: Natural Language :: English
Classifier: Operating System :: POSIX :: Linux
Classifier: Programming Language :: Python :: 3
Classifier: Topic :: Scientific/Engineering :: Bio-Informatics
Requires-Python: >=3.9
License-File: LICENSE.txt
Requires-Dist: numpy<2.0.0,>1.24.0
Requires-Dist: pandas<3.0.0,>=2.0.0
Requires-Dist: tqdm<5.0.0,>=4.0.0
Requires-Dist: tables<4.0.0,>=3.0.0
Requires-Dist: pyrodigal<4.0.0,>=3.0.0
Requires-Dist: networkx<4.0.0,>=3.0.0
Requires-Dist: scipy<2.0.0,>=1.0.0
Requires-Dist: plotly<6.0.0,>=5.0.0
Requires-Dist: gmpy2<3.0.0,>=2.0.0
Requires-Dist: bokeh<4.0.0,>=3.0.0
Provides-Extra: doc
Requires-Dist: sphinx==6.2.1; extra == "doc"
Requires-Dist: sphinx_rtd_theme==1.2.2; extra == "doc"
Requires-Dist: readthedocs-sphinx-search==0.3.2; extra == "doc"
Requires-Dist: sphinx-autobuild==2021.3.14; extra == "doc"
Requires-Dist: myst-parser==2; extra == "doc"
Requires-Dist: docutils==0.18.1; extra == "doc"
Requires-Dist: sphinxcontrib.mermaid==0.9.2; extra == "doc"
Provides-Extra: test
Requires-Dist: pytest==7; extra == "test"
Requires-Dist: black==24.*; extra == "test"
Dynamic: license-file
